odoo10_addon_cmis_stock_production_lot-10.0.1.0.0.99.dev2-py2.7-nspkg.pth
odoo/addons/cmis_stock_production_lot/README.rst
odoo/addons/cmis_stock_production_lot/__init__.py
odoo/addons/cmis_stock_production_lot/__manifest__.py
odoo/addons/cmis_stock_production_lot/i18n/cmis_stock_production_lot.pot
odoo/addons/cmis_stock_production_lot/models/__init__.py
odoo/addons/cmis_stock_production_lot/models/stock_production_lot.py
odoo/addons/cmis_stock_production_lot/readme/CONFIGURE.rst
odoo/addons/cmis_stock_production_lot/readme/CONTRIBUTORS.rst
odoo/addons/cmis_stock_production_lot/readme/DESCRIPTION.rst
odoo/addons/cmis_stock_production_lot/readme/INSTALL.rst
odoo/addons/cmis_stock_production_lot/readme/USAGE.rst
odoo/addons/cmis_stock_production_lot/static/description/icon.png
odoo/addons/cmis_stock_production_lot/views/stock_production_lot.xml
odoo10_addon_cmis_stock_production_lot-10.0.1.0.0.99.dev2.dist-info/METADATA
odoo10_addon_cmis_stock_production_lot-10.0.1.0.0.99.dev2.dist-info/RECORD
odoo10_addon_cmis_stock_production_lot-10.0.1.0.0.99.dev2.dist-info/WHEEL
odoo10_addon_cmis_stock_production_lot-10.0.1.0.0.99.dev2.dist-info/namespace_packages.txt
odoo10_addon_cmis_stock_production_lot-10.0.1.0.0.99.dev2.dist-info/top_level.txt
