Metadata-Version: 2.1
Name: odoo10-addon-cmis-stock-production-lot
Version: 10.0.1.0.0.99.dev2
Summary: Upload CMIS documents on the Lot/SN Number
Home-page: https://github.com/OCA/connector-cmis
Author: Open Source Integrators, Odoo Community Association (OCA)
Author-email: support@odoo-community.org
License: AGPL-3
Platform: UNKNOWN
Classifier: Programming Language :: Python
Classifier: Framework :: Odoo
Classifier: License :: OSI Approved :: GNU Affero General Public License v3
Classifier: Development Status :: 4 - Beta
Requires-Python: ~=2.7
Requires-Dist: odoo10-addon-cmis-web
Requires-Dist: odoo (<10.1dev,>=10.0)
